Metadata-Version: 1.1
Name: rivulet
Version: 0.1.1
Summary: Redis-Based Message Broker for Python
Home-page: https://github.com/mkirchner/rivulet
Author: Marc Kirchner
Author-email: mail@marc-kirchner.de
License: MIT
Platform: UNKNOWN
Classifier: Development Status :: 2 - Pre-Alpha
Classifier: License :: OSI Approved :: MIT License
Classifier: Programming Language :: Python
Classifier: Programming Language :: Python :: 3
Classifier: Programming Language :: Python :: 3.6
Classifier: Programming Language :: Python :: 3.7
